<annotation>
    <folder>Dataset-Palm-Counting2-Kharj</folder>
    <filename>ck2td8cs09cva0944l5ilyvup.mpo</filename>
    <path>/home/riotu/Object Detection/Datasets/Palm_counting/Dataset-Palm-Counting2-Kharj/ck2td8cs09cva0944l5ilyvup.mpo</path>
    <source>
        <database>Unknown</database>
    </source>
    <size>
        <width>4864</width>
        <height>3648</height>
        <depth>3</depth>
    </size>
    <segmented>0</segmented>
    <object>
        <name>Palm</name>
        <pose>Unspecified</pose>
        <truncated>0</truncated>
        <difficult>0</difficult>
        <bndbox>
                <xmin>1622</xmin>
                <ymin>557</ymin>
                <xmax>1949</xmax>
                <ymax>852</ymax>
            </bndbox>
        </object>
    <object>
        <name>Palm</name>
        <pose>Unspecified</pose>
        <truncated>0</truncated>
        <difficult>0</difficult>
        <bndbox>
                <xmin>2064</xmin>
                <ymin>639</ymin>
                <xmax>2281</xmax>
                <ymax>835</ymax>
            </bndbox>
        </object>
    <object>
        <name>Palm</name>
        <pose>Unspecified</pose>
        <truncated>0</truncated>
        <difficult>0</difficult>
        <bndbox>
                <xmin>2433</xmin>
                <ymin>608</ymin>
                <xmax>2796</xmax>
                <ymax>909</ymax>
            </bndbox>
        </object>
    <object>
        <name>Palm</name>
        <pose>Unspecified</pose>
        <truncated>0</truncated>
        <difficult>0</difficult>
        <bndbox>
                <xmin>2904</xmin>
                <ymin>687</ymin>
                <xmax>3127</xmax>
                <ymax>901</ymax>
            </bndbox>
        </object>
    <object>
        <name>Palm</name>
        <pose>Unspecified</pose>
        <truncated>0</truncated>
        <difficult>0</difficult>
        <bndbox>
                <xmin>3280</xmin>
                <ymin>718</ymin>
                <xmax>3577</xmax>
                <ymax>957</ymax>
            </bndbox>
        </object>
    <object>
        <name>Palm</name>
        <pose>Unspecified</pose>
        <truncated>0</truncated>
        <difficult>0</difficult>
        <bndbox>
                <xmin>3734</xmin>
                <ymin>754</ymin>
                <xmax>3995</xmax>
                <ymax>981</ymax>
            </bndbox>
        </object>
    <object>
        <name>Palm</name>
        <pose>Unspecified</pose>
        <truncated>0</truncated>
        <difficult>0</difficult>
        <bndbox>
                <xmin>4089</xmin>
                <ymin>751</ymin>
                <xmax>4445</xmax>
                <ymax>1032</ymax>
            </bndbox>
        </object>
    <object>
        <name>Palm</name>
        <pose>Unspecified</pose>
        <truncated>0</truncated>
        <difficult>0</difficult>
        <bndbox>
                <xmin>4536</xmin>
                <ymin>759</ymin>
                <xmax>4829</xmax>
                <ymax>1044</ymax>
            </bndbox>
        </object>
    <object>
        <name>Palm</name>
        <pose>Unspecified</pose>
        <truncated>0</truncated>
        <difficult>0</difficult>
        <bndbox>
                <xmin>4558</xmin>
                <ymin>346</ymin>
                <xmax>4852</xmax>
                <ymax>635</ymax>
            </bndbox>
        </object>
    <object>
        <name>Palm</name>
        <pose>Unspecified</pose>
        <truncated>0</truncated>
        <difficult>0</difficult>
        <bndbox>
                <xmin>4164</xmin>
                <ymin>345</ymin>
                <xmax>4401</xmax>
                <ymax>564</ymax>
            </bndbox>
        </object>
    <object>
        <name>Palm</name>
        <pose>Unspecified</pose>
        <truncated>0</truncated>
        <difficult>0</difficult>
        <bndbox>
                <xmin>3754</xmin>
                <ymin>288</ymin>
                <xmax>4023</xmax>
                <ymax>546</ymax>
            </bndbox>
        </object>
    <object>
        <name>Palm</name>
        <pose>Unspecified</pose>
        <truncated>0</truncated>
        <difficult>0</difficult>
        <bndbox>
                <xmin>2897</xmin>
                <ymin>235</ymin>
                <xmax>3219</xmax>
                <ymax>538</ymax>
            </bndbox>
        </object>
    <object>
        <name>Palm</name>
        <pose>Unspecified</pose>
        <truncated>0</truncated>
        <difficult>0</difficult>
        <bndbox>
                <xmin>2462</xmin>
                <ymin>202</ymin>
                <xmax>2828</xmax>
                <ymax>514</ymax>
            </bndbox>
        </object>
    <object>
        <name>Palm</name>
        <pose>Unspecified</pose>
        <truncated>0</truncated>
        <difficult>0</difficult>
        <bndbox>
                <xmin>2048</xmin>
                <ymin>134</ymin>
                <xmax>2380</xmax>
                <ymax>453</ymax>
            </bndbox>
        </object>
    <object>
        <name>Palm</name>
        <pose>Unspecified</pose>
        <truncated>0</truncated>
        <difficult>0</difficult>
        <bndbox>
                <xmin>1734</xmin>
                <ymin>214</ymin>
                <xmax>1960</xmax>
                <ymax>425</ymax>
            </bndbox>
        </object>
    <object>
        <name>Palm</name>
        <pose>Unspecified</pose>
        <truncated>0</truncated>
        <difficult>0</difficult>
        <bndbox>
                <xmin>1259</xmin>
                <ymin>113</ymin>
                <xmax>1520</xmax>
                <ymax>371</ymax>
            </bndbox>
        </object>
    <object>
        <name>Palm</name>
        <pose>Unspecified</pose>
        <truncated>0</truncated>
        <difficult>0</difficult>
        <bndbox>
                <xmin>362</xmin>
                <ymin>70</ymin>
                <xmax>709</xmax>
                <ymax>364</ymax>
            </bndbox>
        </object>
    <object>
        <name>Palm</name>
        <pose>Unspecified</pose>
        <truncated>0</truncated>
        <difficult>0</difficult>
        <bndbox>
                <xmin>37</xmin>
                <ymin>75</ymin>
                <xmax>308</xmax>
                <ymax>294</ymax>
            </bndbox>
        </object>
    <object>
        <name>Palm</name>
        <pose>Unspecified</pose>
        <truncated>0</truncated>
        <difficult>0</difficult>
        <bndbox>
                <xmin>322</xmin>
                <ymin>446</ymin>
                <xmax>702</xmax>
                <ymax>756</ymax>
            </bndbox>
        </object>
    <object>
        <name>Palm</name>
        <pose>Unspecified</pose>
        <truncated>0</truncated>
        <difficult>0</difficult>
        <bndbox>
                <xmin>1252</xmin>
                <ymin>561</ymin>
                <xmax>1450</xmax>
                <ymax>792</ymax>
            </bndbox>
        </object>
    <object>
        <name>Palm</name>
        <pose>Unspecified</pose>
        <truncated>0</truncated>
        <difficult>0</difficult>
        <bndbox>
                <xmin>820</xmin>
                <ymin>541</ymin>
                <xmax>1062</xmax>
                <ymax>761</ymax>
            </bndbox>
        </object>
    <object>
        <name>Palm</name>
        <pose>Unspecified</pose>
        <truncated>0</truncated>
        <difficult>0</difficult>
        <bndbox>
                <xmin>41</xmin>
                <ymin>518</ymin>
                <xmax>251</xmax>
                <ymax>697</ymax>
            </bndbox>
        </object>
    <object>
        <name>Palm</name>
        <pose>Unspecified</pose>
        <truncated>0</truncated>
        <difficult>0</difficult>
        <bndbox>
                <xmin>4078</xmin>
                <ymin>1130</ymin>
                <xmax>4518</xmax>
                <ymax>1517</ymax>
            </bndbox>
        </object>
    <object>
        <name>Palm</name>
        <pose>Unspecified</pose>
        <truncated>0</truncated>
        <difficult>0</difficult>
        <bndbox>
                <xmin>3676</xmin>
                <ymin>1113</ymin>
                <xmax>4038</xmax>
                <ymax>1443</ymax>
            </bndbox>
        </object>
    <object>
        <name>Palm</name>
        <pose>Unspecified</pose>
        <truncated>0</truncated>
        <difficult>0</difficult>
        <bndbox>
                <xmin>3208</xmin>
                <ymin>1115</ymin>
                <xmax>3600</xmax>
                <ymax>1460</ymax>
            </bndbox>
        </object>
    <object>
        <name>Palm</name>
        <pose>Unspecified</pose>
        <truncated>0</truncated>
        <difficult>0</difficult>
        <bndbox>
                <xmin>2849</xmin>
                <ymin>1069</ymin>
                <xmax>3169</xmax>
                <ymax>1374</ymax>
            </bndbox>
        </object>
    <object>
        <name>Palm</name>
        <pose>Unspecified</pose>
        <truncated>0</truncated>
        <difficult>0</difficult>
        <bndbox>
                <xmin>2433</xmin>
                <ymin>992</ymin>
                <xmax>2780</xmax>
                <ymax>1347</ymax>
            </bndbox>
        </object>
    <object>
        <name>Palm</name>
        <pose>Unspecified</pose>
        <truncated>0</truncated>
        <difficult>0</difficult>
        <bndbox>
                <xmin>2002</xmin>
                <ymin>1000</ymin>
                <xmax>2329</xmax>
                <ymax>1280</ymax>
            </bndbox>
        </object>
    <object>
        <name>Palm</name>
        <pose>Unspecified</pose>
        <truncated>0</truncated>
        <difficult>0</difficult>
        <bndbox>
                <xmin>1131</xmin>
                <ymin>928</ymin>
                <xmax>1463</xmax>
                <ymax>1243</ymax>
            </bndbox>
        </object>
    <object>
        <name>Palm</name>
        <pose>Unspecified</pose>
        <truncated>0</truncated>
        <difficult>0</difficult>
        <bndbox>
                <xmin>712</xmin>
                <ymin>911</ymin>
                <xmax>1090</xmax>
                <ymax>1233</ymax>
            </bndbox>
        </object>
    <object>
        <name>Palm</name>
        <pose>Unspecified</pose>
        <truncated>0</truncated>
        <difficult>0</difficult>
        <bndbox>
                <xmin>288</xmin>
                <ymin>846</ymin>
                <xmax>681</xmax>
                <ymax>1210</ymax>
            </bndbox>
        </object>
    <object>
        <name>Palm</name>
        <pose>Unspecified</pose>
        <truncated>0</truncated>
        <difficult>0</difficult>
        <bndbox>
                <xmin>353</xmin>
                <ymin>1309</ymin>
                <xmax>647</xmax>
                <ymax>1577</ymax>
            </bndbox>
        </object>
    <object>
        <name>Palm</name>
        <pose>Unspecified</pose>
        <truncated>0</truncated>
        <difficult>0</difficult>
        <bndbox>
                <xmin>1110</xmin>
                <ymin>1348</ymin>
                <xmax>1499</xmax>
                <ymax>1686</ymax>
            </bndbox>
        </object>
    <object>
        <name>Palm</name>
        <pose>Unspecified</pose>
        <truncated>0</truncated>
        <difficult>0</difficult>
        <bndbox>
                <xmin>1573</xmin>
                <ymin>1381</ymin>
                <xmax>1909</xmax>
                <ymax>1704</ymax>
            </bndbox>
        </object>
    <object>
        <name>Palm</name>
        <pose>Unspecified</pose>
        <truncated>0</truncated>
        <difficult>0</difficult>
        <bndbox>
                <xmin>1088</xmin>
                <ymin>1753</ymin>
                <xmax>1426</xmax>
                <ymax>2095</ymax>
            </bndbox>
        </object>
    <object>
        <name>Palm</name>
        <pose>Unspecified</pose>
        <truncated>0</truncated>
        <difficult>0</difficult>
        <bndbox>
                <xmin>1487</xmin>
                <ymin>1797</ymin>
                <xmax>1879</xmax>
                <ymax>2169</ymax>
            </bndbox>
        </object>
    <object>
        <name>Palm</name>
        <pose>Unspecified</pose>
        <truncated>0</truncated>
        <difficult>0</difficult>
        <bndbox>
                <xmin>1958</xmin>
                <ymin>1849</ymin>
                <xmax>2283</xmax>
                <ymax>2115</ymax>
            </bndbox>
        </object>
    <object>
        <name>Palm</name>
        <pose>Unspecified</pose>
        <truncated>0</truncated>
        <difficult>0</difficult>
        <bndbox>
                <xmin>1987</xmin>
                <ymin>1408</ymin>
                <xmax>2287</xmax>
                <ymax>1724</ymax>
            </bndbox>
        </object>
    <object>
        <name>Palm</name>
        <pose>Unspecified</pose>
        <truncated>0</truncated>
        <difficult>0</difficult>
        <bndbox>
                <xmin>2401</xmin>
                <ymin>1490</ymin>
                <xmax>2696</xmax>
                <ymax>1736</ymax>
            </bndbox>
        </object>
    <object>
        <name>Palm</name>
        <pose>Unspecified</pose>
        <truncated>0</truncated>
        <difficult>0</difficult>
        <bndbox>
                <xmin>2834</xmin>
                <ymin>1529</ymin>
                <xmax>3095</xmax>
                <ymax>1748</ymax>
            </bndbox>
        </object>
    <object>
        <name>Palm</name>
        <pose>Unspecified</pose>
        <truncated>0</truncated>
        <difficult>0</difficult>
        <bndbox>
                <xmin>3218</xmin>
                <ymin>1503</ymin>
                <xmax>3605</xmax>
                <ymax>1859</ymax>
            </bndbox>
        </object>
    <object>
        <name>Palm</name>
        <pose>Unspecified</pose>
        <truncated>0</truncated>
        <difficult>0</difficult>
        <bndbox>
                <xmin>3689</xmin>
                <ymin>1538</ymin>
                <xmax>4011</xmax>
                <ymax>1828</ymax>
            </bndbox>
        </object>
    <object>
        <name>Palm</name>
        <pose>Unspecified</pose>
        <truncated>0</truncated>
        <difficult>0</difficult>
        <bndbox>
                <xmin>2804</xmin>
                <ymin>1901</ymin>
                <xmax>3101</xmax>
                <ymax>2213</ymax>
            </bndbox>
        </object>
    <object>
        <name>Palm</name>
        <pose>Unspecified</pose>
        <truncated>0</truncated>
        <difficult>0</difficult>
        <bndbox>
                <xmin>2354</xmin>
                <ymin>1865</ymin>
                <xmax>2723</xmax>
                <ymax>2198</ymax>
            </bndbox>
        </object>
    <object>
        <name>Palm</name>
        <pose>Unspecified</pose>
        <truncated>0</truncated>
        <difficult>0</difficult>
        <bndbox>
                <xmin>1894</xmin>
                <ymin>2266</ymin>
                <xmax>2247</xmax>
                <ymax>2570</ymax>
            </bndbox>
        </object>
    <object>
        <name>Palm</name>
        <pose>Unspecified</pose>
        <truncated>0</truncated>
        <difficult>0</difficult>
        <bndbox>
                <xmin>2344</xmin>
                <ymin>2297</ymin>
                <xmax>2692</xmax>
                <ymax>2596</ymax>
            </bndbox>
        </object>
    <object>
        <name>Palm</name>
        <pose>Unspecified</pose>
        <truncated>0</truncated>
        <difficult>0</difficult>
        <bndbox>
                <xmin>2734</xmin>
                <ymin>2281</ymin>
                <xmax>3130</xmax>
                <ymax>2661</ymax>
            </bndbox>
        </object>
    <object>
        <name>Palm</name>
        <pose>Unspecified</pose>
        <truncated>0</truncated>
        <difficult>0</difficult>
        <bndbox>
                <xmin>3143</xmin>
                <ymin>2315</ymin>
                <xmax>3566</xmax>
                <ymax>2697</ymax>
            </bndbox>
        </object>
    <object>
        <name>Palm</name>
        <pose>Unspecified</pose>
        <truncated>0</truncated>
        <difficult>0</difficult>
        <bndbox>
                <xmin>3200</xmin>
                <ymin>1945</ymin>
                <xmax>3556</xmax>
                <ymax>2256</ymax>
            </bndbox>
        </object>
    <object>
        <name>Palm</name>
        <pose>Unspecified</pose>
        <truncated>0</truncated>
        <difficult>0</difficult>
        <bndbox>
                <xmin>3644</xmin>
                <ymin>1964</ymin>
                <xmax>3951</xmax>
                <ymax>2260</ymax>
            </bndbox>
        </object>
    <object>
        <name>Palm</name>
        <pose>Unspecified</pose>
        <truncated>0</truncated>
        <difficult>0</difficult>
        <bndbox>
                <xmin>4032</xmin>
                <ymin>2000</ymin>
                <xmax>4389</xmax>
                <ymax>2304</ymax>
            </bndbox>
        </object>
    <object>
        <name>Palm</name>
        <pose>Unspecified</pose>
        <truncated>0</truncated>
        <difficult>0</difficult>
        <bndbox>
                <xmin>3622</xmin>
                <ymin>2390</ymin>
                <xmax>3971</xmax>
                <ymax>2734</ymax>
            </bndbox>
        </object>
    <object>
        <name>Palm</name>
        <pose>Unspecified</pose>
        <truncated>0</truncated>
        <difficult>0</difficult>
        <bndbox>
                <xmin>4456</xmin>
                <ymin>2041</ymin>
                <xmax>4859</xmax>
                <ymax>2357</ymax>
            </bndbox>
        </object>
    <object>
        <name>Palm</name>
        <pose>Unspecified</pose>
        <truncated>0</truncated>
        <difficult>0</difficult>
        <bndbox>
                <xmin>4456</xmin>
                <ymin>2486</ymin>
                <xmax>4691</xmax>
                <ymax>2721</ymax>
            </bndbox>
        </object>
    <object>
        <name>Palm</name>
        <pose>Unspecified</pose>
        <truncated>0</truncated>
        <difficult>0</difficult>
        <bndbox>
                <xmin>4034</xmin>
                <ymin>2913</ymin>
                <xmax>4275</xmax>
                <ymax>3120</ymax>
            </bndbox>
        </object>
    <object>
        <name>Palm</name>
        <pose>Unspecified</pose>
        <truncated>0</truncated>
        <difficult>0</difficult>
        <bndbox>
                <xmin>4436</xmin>
                <ymin>2877</ymin>
                <xmax>4831</xmax>
                <ymax>3256</ymax>
            </bndbox>
        </object>
    <object>
        <name>Palm</name>
        <pose>Unspecified</pose>
        <truncated>0</truncated>
        <difficult>0</difficult>
        <bndbox>
                <xmin>4411</xmin>
                <ymin>3342</ymin>
                <xmax>4725</xmax>
                <ymax>3613</ymax>
            </bndbox>
        </object>
    <object>
        <name>Palm</name>
        <pose>Unspecified</pose>
        <truncated>0</truncated>
        <difficult>0</difficult>
        <bndbox>
                <xmin>3973</xmin>
                <ymin>3239</ymin>
                <xmax>4365</xmax>
                <ymax>3628</ymax>
            </bndbox>
        </object>
    <object>
        <name>Palm</name>
        <pose>Unspecified</pose>
        <truncated>0</truncated>
        <difficult>0</difficult>
        <bndbox>
                <xmin>3532</xmin>
                <ymin>3208</ymin>
                <xmax>3924</xmax>
                <ymax>3602</ymax>
            </bndbox>
        </object>
    <object>
        <name>Palm</name>
        <pose>Unspecified</pose>
        <truncated>0</truncated>
        <difficult>0</difficult>
        <bndbox>
                <xmin>3154</xmin>
                <ymin>3243</ymin>
                <xmax>3447</xmax>
                <ymax>3475</ymax>
            </bndbox>
        </object>
    <object>
        <name>Palm</name>
        <pose>Unspecified</pose>
        <truncated>0</truncated>
        <difficult>0</difficult>
        <bndbox>
                <xmin>2758</xmin>
                <ymin>3221</ymin>
                <xmax>3030</xmax>
                <ymax>3503</ymax>
            </bndbox>
        </object>
    <object>
        <name>Palm</name>
        <pose>Unspecified</pose>
        <truncated>0</truncated>
        <difficult>0</difficult>
        <bndbox>
                <xmin>2215</xmin>
                <ymin>3163</ymin>
                <xmax>2648</xmax>
                <ymax>3512</ymax>
            </bndbox>
        </object>
    <object>
        <name>Palm</name>
        <pose>Unspecified</pose>
        <truncated>0</truncated>
        <difficult>0</difficult>
        <bndbox>
                <xmin>2286</xmin>
                <ymin>2726</ymin>
                <xmax>2674</xmax>
                <ymax>3045</ymax>
            </bndbox>
        </object>
    <object>
        <name>Palm</name>
        <pose>Unspecified</pose>
        <truncated>0</truncated>
        <difficult>0</difficult>
        <bndbox>
                <xmin>1019</xmin>
                <ymin>2626</ymin>
                <xmax>1381</xmax>
                <ymax>2922</ymax>
            </bndbox>
        </object>
    <object>
        <name>Palm</name>
        <pose>Unspecified</pose>
        <truncated>0</truncated>
        <difficult>0</difficult>
        <bndbox>
                <xmin>1030</xmin>
                <ymin>3044</ymin>
                <xmax>1349</xmax>
                <ymax>3348</ymax>
            </bndbox>
        </object>
    <object>
        <name>Palm</name>
        <pose>Unspecified</pose>
        <truncated>0</truncated>
        <difficult>0</difficult>
        <bndbox>
                <xmin>683</xmin>
                <ymin>2612</ymin>
                <xmax>942</xmax>
                <ymax>2838</ymax>
            </bndbox>
        </object>
    <object>
        <name>Palm</name>
        <pose>Unspecified</pose>
        <truncated>0</truncated>
        <difficult>0</difficult>
        <bndbox>
                <xmin>711</xmin>
                <ymin>2196</ymin>
                <xmax>989</xmax>
                <ymax>2402</ymax>
            </bndbox>
        </object>
    <object>
        <name>Palm</name>
        <pose>Unspecified</pose>
        <truncated>0</truncated>
        <difficult>0</difficult>
        <bndbox>
                <xmin>1129</xmin>
                <ymin>2222</ymin>
                <xmax>1392</xmax>
                <ymax>2456</ymax>
            </bndbox>
        </object>
    <object>
        <name>Palm</name>
        <pose>Unspecified</pose>
        <truncated>0</truncated>
        <difficult>0</difficult>
        <bndbox>
                <xmin>679</xmin>
                <ymin>1749</ymin>
                <xmax>996</xmax>
                <ymax>2015</ymax>
            </bndbox>
        </object>
    <object>
        <name>Palm</name>
        <pose>Unspecified</pose>
        <truncated>0</truncated>
        <difficult>0</difficult>
        <bndbox>
                <xmin>224</xmin>
                <ymin>1687</ymin>
                <xmax>621</xmax>
                <ymax>1982</ymax>
            </bndbox>
        </object>
    <object>
        <name>Palm</name>
        <pose>Unspecified</pose>
        <truncated>0</truncated>
        <difficult>0</difficult>
        <bndbox>
                <xmin>233</xmin>
                <ymin>2122</ymin>
                <xmax>590</xmax>
                <ymax>2396</ymax>
            </bndbox>
        </object>
    <object>
        <name>Palm</name>
        <pose>Unspecified</pose>
        <truncated>0</truncated>
        <difficult>0</difficult>
        <bndbox>
                <xmin>276</xmin>
                <ymin>2581</ymin>
                <xmax>556</xmax>
                <ymax>2853</ymax>
            </bndbox>
        </object>
    <object>
        <name>Palm</name>
        <pose>Unspecified</pose>
        <truncated>0</truncated>
        <difficult>0</difficult>
        <bndbox>
                <xmin>620</xmin>
                <ymin>3017</ymin>
                <xmax>948</xmax>
                <ymax>3279</ymax>
            </bndbox>
        </object>
    <object>
        <name>Palm</name>
        <pose>Unspecified</pose>
        <truncated>0</truncated>
        <difficult>0</difficult>
        <bndbox>
                <xmin>203</xmin>
                <ymin>3003</ymin>
                <xmax>504</xmax>
                <ymax>3269</ymax>
            </bndbox>
        </object>
    <object>
        <name>Palm</name>
        <pose>Unspecified</pose>
        <truncated>0</truncated>
        <difficult>0</difficult>
        <bndbox>
                <xmin>601</xmin>
                <ymin>3437</ymin>
                <xmax>899</xmax>
                <ymax>3643</ymax>
            </bndbox>
        </object>
    <object>
        <name>Palm</name>
        <pose>Unspecified</pose>
        <truncated>0</truncated>
        <difficult>0</difficult>
        <bndbox>
                <xmin>4577</xmin>
                <ymin>0</ymin>
                <xmax>4864</xmax>
                <ymax>235</ymax>
            </bndbox>
        </object>
    <object>
        <name>Palm</name>
        <pose>Unspecified</pose>
        <truncated>0</truncated>
        <difficult>0</difficult>
        <bndbox>
                <xmin>4524</xmin>
                <ymin>1683</ymin>
                <xmax>4772</xmax>
                <ymax>1904</ymax>
            </bndbox>
        </object>
    </annotation>
