<annotation>
    <folder>From_Labelbox-PSU-palms</folder>
    <filename>ck4cixeqg6pxq08867ymr7gd4.jpeg</filename>
    <path>/home/riotu/Object Detection/Datasets/Palm_counting/From_Labelbox-PSU-palms/ck4cixeqg6pxq08867ymr7gd4.jpeg</path>
    <source>
        <database>Unknown</database>
    </source>
    <size>
        <width>4096</width>
        <height>2160</height>
        <depth>3</depth>
    </size>
    <segmented>0</segmented>
    <object>
        <name>Palm</name>
        <pose>Unspecified</pose>
        <truncated>0</truncated>
        <difficult>0</difficult>
        <bndbox>
                <xmin>970</xmin>
                <ymin>425</ymin>
                <xmax>1133</xmax>
                <ymax>608</ymax>
            </bndbox>
        </object>
    <object>
        <name>Palm</name>
        <pose>Unspecified</pose>
        <truncated>0</truncated>
        <difficult>0</difficult>
        <bndbox>
                <xmin>1992</xmin>
                <ymin>310</ymin>
                <xmax>2347</xmax>
                <ymax>686</ymax>
            </bndbox>
        </object>
    <object>
        <name>Palm</name>
        <pose>Unspecified</pose>
        <truncated>0</truncated>
        <difficult>0</difficult>
        <bndbox>
                <xmin>1256</xmin>
                <ymin>1611</ymin>
                <xmax>1445</xmax>
                <ymax>1788</ymax>
            </bndbox>
        </object>
    <object>
        <name>Palm</name>
        <pose>Unspecified</pose>
        <truncated>0</truncated>
        <difficult>0</difficult>
        <bndbox>
                <xmin>1400</xmin>
                <ymin>1679</ymin>
                <xmax>1600</xmax>
                <ymax>1860</ymax>
            </bndbox>
        </object>
    <object>
        <name>Palm</name>
        <pose>Unspecified</pose>
        <truncated>0</truncated>
        <difficult>0</difficult>
        <bndbox>
                <xmin>1598</xmin>
                <ymin>1616</ymin>
                <xmax>1806</xmax>
                <ymax>1847</ymax>
            </bndbox>
        </object>
    <object>
        <name>Palm</name>
        <pose>Unspecified</pose>
        <truncated>0</truncated>
        <difficult>0</difficult>
        <bndbox>
                <xmin>1237</xmin>
                <ymin>1832</ymin>
                <xmax>1448</xmax>
                <ymax>1990</ymax>
            </bndbox>
        </object>
    <object>
        <name>Palm</name>
        <pose>Unspecified</pose>
        <truncated>0</truncated>
        <difficult>0</difficult>
        <bndbox>
                <xmin>1584</xmin>
                <ymin>1838</ymin>
                <xmax>1745</xmax>
                <ymax>1996</ymax>
            </bndbox>
        </object>
    <object>
        <name>Palm</name>
        <pose>Unspecified</pose>
        <truncated>0</truncated>
        <difficult>0</difficult>
        <bndbox>
                <xmin>1395</xmin>
                <ymin>1868</ymin>
                <xmax>1576</xmax>
                <ymax>2061</ymax>
            </bndbox>
        </object>
    <object>
        <name>Palm</name>
        <pose>Unspecified</pose>
        <truncated>0</truncated>
        <difficult>0</difficult>
        <bndbox>
                <xmin>1248</xmin>
                <ymin>2036</ymin>
                <xmax>1495</xmax>
                <ymax>2153</ymax>
            </bndbox>
        </object>
    <object>
        <name>Palm</name>
        <pose>Unspecified</pose>
        <truncated>0</truncated>
        <difficult>0</difficult>
        <bndbox>
                <xmin>1488</xmin>
                <ymin>1975</ymin>
                <xmax>1685</xmax>
                <ymax>2160</ymax>
            </bndbox>
        </object>
    <object>
        <name>Palm</name>
        <pose>Unspecified</pose>
        <truncated>0</truncated>
        <difficult>0</difficult>
        <bndbox>
                <xmin>1633</xmin>
                <ymin>2005</ymin>
                <xmax>1818</xmax>
                <ymax>2159</ymax>
            </bndbox>
        </object>
    </annotation>
